kpi_repository_client/__init__.py
kpi_repository_client/dot4_client.py
kpi_repository_client/kpi_client_exception.py
kpi_repository_client/kpi_definition.py
kpi_repository_client/kpi_repository_client.py
kpi_repository_client/kpi_values.py
kpi_repository_client/service.py
kpi_repository_client-1.0.0.3.dist-info/DESCRIPTION.rst
kpi_repository_client-1.0.0.3.dist-info/METADATA
kpi_repository_client-1.0.0.3.dist-info/RECORD
kpi_repository_client-1.0.0.3.dist-info/WHEEL
kpi_repository_client-1.0.0.3.dist-info/metadata.json
kpi_repository_client-1.0.0.3.dist-info/top_level.txt
