Metadata-Version: 2.0
Name: kpi-repository-client
Version: 1.0.0.3
Summary: Python client for KpiRepository
Home-page: https://www.realtech.com
Author: REALTECH AG
Author-email: info@realtech.com
License: UNKNOWN
Platform: UNKNOWN
Classifier: Programming Language :: Python :: 3
Classifier: License :: OSI Approved :: MIT License
Classifier: Operating System :: OS Independent
